{
  "project_info": {
    "project_number": "406423914851",
    "project_id": "ui-drive-eed69",
    "storage_bucket": "ui-drive-eed69.firebasestorage.app"
  },
  "client": [
    {
      "client_info": {
        "mobilesdk_app_id": "1:406423914851:android:e53d94134d015c986c2b56",
        "android_client_info": {
          "package_name": "com.uidrive.user"
        }
      },
      "oauth_client": [],
      "api_key": [
        {
          "current_key": "AIzaSyBMkRHJ0QRYN9ENY4NNC3qykmvA7T3-F8s"
        }
      ],
      "services": {
        "appinvite_service": {
          "other_platform_oauth_client": []
        }
      }
    }
  ],
  "configuration_version": "1"
}